chronox/__init__.py
chronox/chronos.py
chronox/exceptions.py
chronox/mark.py
chronox/utils.py
chronox/calendar/calendar.py
chronox/calendar/day.py
chronox/calendar/month.py
chronox/calendar/node.py
chronox/calendar/week.py
chronox/calendar/year.py
chronox/clock/clock.py
chronox/clock/hand.py
chronox/parser/calc.py
chronox/parser/datetime.py
chronox/parser/specs/period.py
chronox/parser/specs/point.py
chronox/parser/specs/scope.py
chronox_python-1.0.0.dist-info/METADATA
chronox_python-1.0.0.dist-info/WHEEL
chronox_python-1.0.0.dist-info/top_level.txt
chronox_python-1.0.0.dist-info/RECORD
