Metadata-Version: 2.1
Name: chronox-python
Version: 1.0.0
Summary: An innovated and extended periodic cron time utility, it provides more expressive power by using expression similar to cron and optimized algorithm implementation for large number of steps search.
Home-page: https://github.com/RobbieL-nlp/ChronoX-python
Author: RobbieL-nlp
Keywords: cron,chronos,period,time,date,datetime,chronox
Requires-Python: >=3.8
